ezoutlet/__init__.py
ezoutlet/__main__.py
ezoutlet/constants.py
ezoutlet/error_handling.py
ezoutlet/exceptions.py
ezoutlet/ez_outlet.py
ezoutlet/icommand.py
ezoutlet/no_command.py
ezoutlet/parse_command.py
ezoutlet/parser.py
ezoutlet/reset_command.py
ezoutlet/commands/__init__.py
ezoutlet/commands/icommand.py
ezoutlet/commands/no_command.py
ezoutlet/commands/parse_command.py
ezoutlet/commands/reset_command.py
ezoutlet/commands/version_command.py
ezoutlet-1.0.dist-info/DESCRIPTION.rst
ezoutlet-1.0.dist-info/METADATA
ezoutlet-1.0.dist-info/RECORD
ezoutlet-1.0.dist-info/WHEEL
ezoutlet-1.0.dist-info/metadata.json
ezoutlet-1.0.dist-info/top_level.txt
