Metadata-Version: 2.0
Name: ezoutlet
Version: 1.0
Summary: Command line tool and Python API for ezOutlet EZ-11b
Home-page: https://github.com/jtpereyda/ezoutlet
Author: Joshua Pereyda
Author-email: joshua.t.pereyda@gmail.com
License: MIT
Platform: UNKNOWN
Classifier: Development Status :: 4 - Beta
Classifier: Environment :: Console
Classifier: Intended Audience :: Developers
Classifier: Intended Audience :: Science/Research
Classifier: License :: OSI Approved :: MIT License
Classifier: Natural Language :: English
Classifier: Operating System :: OS Independent
Classifier: Programming Language :: Python
Classifier: Programming Language :: Python :: 2.7
Classifier: Topic :: Security
Classifier: Topic :: Software Development :: Testing :: Traffic Generation
Requires-Dist: future
Requires-Dist: requests
Provides-Extra: dev
Requires-Dist: mock; extra == 'dev'
Requires-Dist: pytest; extra == 'dev'
